{
    "grid_values": {
        "C": [
            0.001,
            0.01,
            0.1,
            1.0,
            10.0,
            100.0,
            1000.0,
            5714.28
        ],
        "penalty": [
            "l2",
            "l1",
            "none"
        ]
    },
    "k_1": {
        "params": {
            "C": 0.001,
            "penalty": "none"
        },
        "f1": 0.6391371003663292
    },
    "k_2": {
        "params": {
            "C": 0.001,
            "penalty": "none"
        },
        "f1": 0.634534345044511
    },
    "k_3": {
        "params": {
            "C": 0.001,
            "penalty": "none"
        },
        "f1": 0.6482784885173427
    },
    "k_4": {
        "params": {
            "C": 0.001,
            "penalty": "none"
        },
        "f1": 0.6245287371175856
    },
    "k_5": {
        "params": {
            "C": 5714.28,
            "penalty": "l2"
        },
        "f1": 0.6538445759448078
    },
    "k_6": {
        "params": {
            "C": 1000.0,
            "penalty": "l2"
        },
        "f1": 0.6402455706534363
    },
    "k_7": {
        "params": {
            "C": 0.001,
            "penalty": "none"
        },
        "f1": 0.6411112587381268
    },
    "k_8": {
        "params": {
            "C": 5714.28,
            "penalty": "l2"
        },
        "f1": 0.6115008890538149
    },
    "k_9": {
        "params": {
            "C": 100.0,
            "penalty": "l2"
        },
        "f1": 0.6034732140550556
    },
    "k_10": {
        "params": {
            "C": 0.001,
            "penalty": "none"
        },
        "f1": 0.6552307062609333
    },
    "time": "3.0min21.45s"
}