{
    "grid_values": {
        "C": [
            0.001,
            0.01,
            0.1,
            1.0,
            10.0,
            100.0,
            1000.0,
            5714.28
        ],
        "penalty": [
            "l2",
            "l1",
            "none"
        ]
    },
    "k_1": {
        "params": {
            "C": 5714.28,
            "penalty": "l2"
        },
        "f1": 0.6348597303008268
    },
    "k_2": {
        "params": {
            "C": 100.0,
            "penalty": "l2"
        },
        "f1": 0.6400886334134989
    },
    "k_3": {
        "params": {
            "C": 0.001,
            "penalty": "none"
        },
        "f1": 0.6428619843553273
    },
    "k_4": {
        "params": {
            "C": 5714.28,
            "penalty": "l2"
        },
        "f1": 0.6208882145705391
    },
    "k_5": {
        "params": {
            "C": 0.001,
            "penalty": "none"
        },
        "f1": 0.6375556523229613
    },
    "k_6": {
        "params": {
            "C": 0.001,
            "penalty": "none"
        },
        "f1": 0.6111812530942623
    },
    "k_7": {
        "params": {
            "C": 0.001,
            "penalty": "none"
        },
        "f1": 0.6524728896251959
    },
    "k_8": {
        "params": {
            "C": 0.001,
            "penalty": "none"
        },
        "f1": 0.6245118938985246
    },
    "k_9": {
        "params": {
            "C": 0.001,
            "penalty": "none"
        },
        "f1": 0.6411544274963233
    },
    "k_10": {
        "params": {
            "C": 0.001,
            "penalty": "none"
        },
        "f1": 0.6169102766100536
    },
    "time": "3.0min44.48s"
}